gambitparser.py
gambitparser-0.0.4.dist-info/License.txt
gambitparser-0.0.4.dist-info/METADATA
gambitparser-0.0.4.dist-info/WHEEL
gambitparser-0.0.4.dist-info/top_level.txt
gambitparser-0.0.4.dist-info/RECORD
