Metadata-Version: 2.1
Name: gambitparser
Version: 0.0.4
Summary: An efficent gambit parser for simple, perfect information games
Home-page: https://github.com/baileymorton989/gambitparser
Author: Bailey Morton
Author-email: baileymorton989@gmail.com
License: MIT License
Platform: UNKNOWN
Classifier: Programming Language :: Python :: 3
Classifier: Programming Language :: Python :: 3.6
Classifier: Programming Language :: Python :: 3.7
Classifier: Programming Language :: Python :: 3.8
Classifier: Programming Language :: Python :: 3.9
Classifier: License :: OSI Approved :: MIT License
Classifier: Operating System :: OS Independent
Requires-Dist: gambit (>=16.0.1)
Requires-Dist: pandas (>=0.24.2)
Requires-Dist: numpy (>=1.16.6)
Requires-Dist: argparse (>=1.1)
Provides-Extra: dev
Requires-Dist: pytest (>3.7) ; extra == 'dev'
